natari/__init__.py
natari/_function.py
natari/_utils.py
natari/cell_counting_arcade.py
natari/ping_pong.py
natari/sliding_puzzle.py
natari/snake.py
natari/data/IXMtest_A02_s9.tif
natari/data/IXMtest_A02_s9_image_data_source.txt
natari-0.2.7.dist-info/METADATA
natari-0.2.7.dist-info/WHEEL
natari-0.2.7.dist-info/entry_points.txt
natari-0.2.7.dist-info/license
natari-0.2.7.dist-info/top_level.txt
natari-0.2.7.dist-info/RECORD
