Metadata-Version: 2.1
Name: natari
Version: 0.2.7
Summary: Napari gaming
Home-page: https://github.com/haesleinhuepf/natari
Author: Robert Haase
Author-email: robert.haase@tu-dresden.de
License: BSD-3-Clause
Project-URL: Bug Tracker, https://github.com/haesleinhuepf/natari/issues
Project-URL: Documentation, https://github.com/haesleinhuepf/natari#README.md
Project-URL: Source Code, https://github.com/haesleinhuepf/natari
Project-URL: User Support, https://github.com/haesleinhuepf/natari/issues
Platform: UNKNOWN
Classifier: Development Status :: 3 - Alpha
Classifier: Intended Audience :: Developers
Classifier: Framework :: napari
Classifier: Topic :: Software Development :: Testing
Classifier: Programming Language :: Python
Classifier: Programming Language :: Python :: 3
Classifier: Programming Language :: Python :: 3.7
Classifier: Programming Language :: Python :: 3.8
Classifier: Programming Language :: Python :: 3.9
Classifier: Operating System :: OS Independent
Classifier: License :: OSI Approved :: BSD License
Requires-Python: >=3.7
License-File: license
Requires-Dist: napari-plugin-engine (>=0.1.4)
Requires-Dist: numpy
Requires-Dist: napari
Requires-Dist: scipy
Requires-Dist: napari-tools-menu
